{
    "file_path": "docs_src\\extra_data_types\\tutorial001_py310.py",
    "elements": [
        {
            "type": "function",
            "is_async": true,
            "name": "read_items",
            "docstring": "",
            "args": [
                {
                    "name": "item_id",
                    "type": "UUID"
                },
                {
                    "name": "start_datetime",
                    "type": "datetime"
                },
                {
                    "name": "end_datetime",
                    "type": "datetime"
                },
                {
                    "name": "process_after",
                    "type": "timedelta"
                },
                {
                    "name": "repeat_at",
                    "type": "time | None"
                }
            ],
            "return_type": "",
            "line_number": 10
        }
    ]
}